mahjong/__init__.py
mahjong/tenhou_record_check.py
mahjong/universe_paifu_convert.py
mahjong/win_rate_demo.py
mahjong/container/__init__.py
mahjong/container/distribution.py
mahjong/container/set.py
mahjong/container/utils.py
mahjong/container/pattern/__init__.py
mahjong/container/pattern/reasoning.py
mahjong/container/pattern/win.py
mahjong/record/__init__.py
mahjong/record/category.py
mahjong/record/checker.py
mahjong/record/const.py
mahjong/record/player.py
mahjong/record/reader.py
mahjong/record/stage.py
mahjong/record/state.py
mahjong/record/util_functions.py
mahjong/record/universe/__init__.py
mahjong/record/universe/command.py
mahjong/record/universe/executor.py
mahjong/record/universe/format.py
mahjong/record/universe/interpreter.py
mahjong/record/universe/property_manager.py
mahjong/record/universe/translator.py
mahjong/record/universe/tenhou/__init__.py
mahjong/record/universe/tenhou/event_definition.py
mahjong/record/universe/tenhou/xml_macher.py
mahjong/record/utils/__init__.py
mahjong/record/utils/bit.py
mahjong/record/utils/builder.py
mahjong/record/utils/constant.py
mahjong/record/utils/event.py
mahjong/record/utils/value/__init__.py
mahjong/record/utils/value/gametype.py
mahjong/record/utils/value/general.py
mahjong/record/utils/value/meld.py
mahjong/record/utils/value/tile.py
mahjong/templates/__init__.py
mahjong/templates/record_checker_template.html
mahjong/templates/mjpic/0m.png
mahjong/templates/mjpic/0p.png
mahjong/templates/mjpic/0s.png
mahjong/templates/mjpic/1m.png
mahjong/templates/mjpic/1p.png
mahjong/templates/mjpic/1s.png
mahjong/templates/mjpic/1z.png
mahjong/templates/mjpic/2m.png
mahjong/templates/mjpic/2p.png
mahjong/templates/mjpic/2s.png
mahjong/templates/mjpic/2z.png
mahjong/templates/mjpic/3m.png
mahjong/templates/mjpic/3p.png
mahjong/templates/mjpic/3s.png
mahjong/templates/mjpic/3z.png
mahjong/templates/mjpic/4m.png
mahjong/templates/mjpic/4p.png
mahjong/templates/mjpic/4s.png
mahjong/templates/mjpic/4z.png
auto_white_reimu-0.2.2.dist-info/LICENSE
auto_white_reimu-0.2.2.dist-info/METADATA
auto_white_reimu-0.2.2.dist-info/WHEEL
auto_white_reimu-0.2.2.dist-info/entry_points.txt
auto_white_reimu-0.2.2.dist-info/top_level.txt
auto_white_reimu-0.2.2.dist-info/RECORD
