Metadata-Version: 2.1
Name: auto-white-reimu
Version: 0.2.2
Summary: UNKNOWN
Home-page: UNKNOWN
Author: Ledenel
Author-email: ledenelintelli@gmail.com
License: GPL
Platform: UNKNOWN
Requires-Dist: numpy
Requires-Dist: bitstruct
Requires-Dist: requests
Requires-Dist: jinja2
Requires-Dist: loguru
Requires-Dist: pandas
Provides-Extra: dev
Requires-Dist: pipenv-setup ; extra == 'dev'
Provides-Extra: test
Requires-Dist: pytest ; extra == 'test'
Requires-Dist: pandas ; extra == 'test'
Requires-Dist: beautifulsoup4 ; extra == 'test'
